Testsuite: gov.nasa.jpf.test.mc.basic.LocalVarInfoTest
Tests run: 1, Failures: 0, Errors: 0, Skipped: 0, Time elapsed: 2.975 sec
------------- Standard Output ---------------
  running jpf with args: +listener=.test.mc.basic.LocalVarInfoTest$TestLookupListener
JavaPathfinder core system v8.0 (rev 32+) - (C) 2005-2014 United States Government. All rights reserved.


====================================================== system under test
gov.nasa.jpf.test.mc.basic.LocalVarInfoTest.runTestMethod()

====================================================== search started: 9/7/17 11:24 AM
---- testLookup()V entered
 LocalVarInfos (should have {'this', 'x', 'y'} : 
    LocalVarInfo[name="x",signature="I",startPC=19,endPC=27,slotIndex=1]
    LocalVarInfo[name="y",signature="I",startPC=21,endPC=27,slotIndex=2]
    LocalVarInfo[name="this",signature="Lgov/nasa/jpf/test/mc/basic/LocalVarInfoTest;",startPC=0,endPC=38,slotIndex=0]

  0: aload_0 : LocalVarInfo[name="this",signature="Lgov/nasa/jpf/test/mc/basic/LocalVarInfoTest;",startPC=0,endPC=38,slotIndex=0]
  1: iconst_1
  2: anewarray
  5: dup
  6: iconst_0
  7: ldc
  9: aastore
 10: invokevirtual gov.nasa.jpf.test.mc.basic.LocalVarInfoTest.verifyNoPropertyViolation([Ljava/lang/String;)Z
 13: ifeq 28
 16: bipush
 18: istore_1 : LocalVarInfo[name="x",signature="I",startPC=19,endPC=27,slotIndex=1]
 19: iload_1 : LocalVarInfo[name="x",signature="I",startPC=19,endPC=27,slotIndex=1]
 20: istore_2 : LocalVarInfo[name="y",signature="I",startPC=21,endPC=27,slotIndex=2]
 21: getstatic java.lang.System.out
 24: iload_2 : LocalVarInfo[name="y",signature="I",startPC=21,endPC=27,slotIndex=2]
 25: invokevirtual java.io.PrintStream.println(I)V
42
 28: invokestatic gov.nasa.jpf.test.mc.basic.LocalVarInfoTest.isJPFRun()Z
 31: ifne 38

====================================================== results
no errors detected

====================================================== search finished: 9/7/17 11:24 AM
--- local var access log: 
ALOAD this
ISTORE x
ILOAD x
ISTORE y
ILOAD y
------------- ---------------- ---------------

Testcase: testLookup took 2.914 sec
